Workbook

Sheet Jan 2025
B2: HLN Solutions | I2: HLN Solutions
B3: Etat de resultats | I3: Etat des capitaux propres
B4: Pour la periode terminant le 31 Jan 2025 | I4: Pour la periode terminant le 31 Jan 2025
B5: VENTES BRUTES | E5: 54950 | I5: Capital initial | L5: 955494.65
B6: Cout des Marchandises Vendues(CMV) | C6: 38404.2 | I6: Apports | L6: =10000+149684.5427 -> 159684.54
B7: Cout des Produits Vendus | E7: =C6 -> 38404.2 | I7: Perte nette | L7: =E18 -> -31696.466
B8: MARGE BENEFICIAIRE BRUTE | E8: =E5-C6 -> 16545.8 | I8: Capital au 31 Jan 2025 | L8: =SUM(L5:L7) -> 1083482.7
B9: Couts d'exploitation
B10: Salaires | C10: 25000
B11: Loyer | C11: ='[1]Tableau d''amortissement loyer'!$D$4 -> 8333.3333
B12: Publicite | C12: =(20802.71/12)+(40756/12)+(29040/12) -> 7549.8925
B13: Amortissements & Depreciations | C13: =25692.72 -> 25692.72
B14: Autres depenses | C14: =30000/12+11650/12 -> 3470.8333
B15: Total des couts d'Exploitation | E15: =SUM(C10:D13) -> 66575.946
B16: Perte nette | E16: =E8-E15 -> -50030.146
B17: Revenus hors activites | C17: =18000+333.68 -> 18333.68 | E17: =C17 -> 18333.68
B18: Resultat de la periode | E18: =E16+E17 -> -31696.466 | M18: Bilan
H19: =25000+1350+2690 -> 29040 | M19: Au 31 Jan 2025
M20: ACTIF | N20: Brut | O20: Amort/ Deprec | P20: Net | Q20: PASSIF
M21: Actif Immobilisé | Q21: Capitaux Propres | S21: =+R22+R25+R24 -> 653757.48
M22: Immobilisations incorporelles | Q22: Capital | R22: =L5+L6 -> 1115179.2
M23: Frais d'Etablissements | N23: =1250+10000+10518+1250+5500+20000+82292.65+41282.51+80302.31 -> 252395.47 | O23: =(N23/48)*13 -> 68357.106 | P23: =N23-O23 -> 184038.36 | Q23: Reserves | R23: 0
M24: Amenagements et decorations | N24: =15000+11000 -> 26000 | O24: =(N24/18)*13 -> 18777.778 | P24: =N24-O24 -> 7222.2222 | Q24: Report a nouveau | R24: =-386036.46-13500-27500-37359.67-88819.54+33613.94-29972.5+87532.4+56880.81+36807.67+9938.26+10872.6+15048.45-17021.9-80209.31 -> -429725.25
M25: Frais activation lapoula & impression | N25: =11650 -> 11650 | O25: =(N25/12)*1 -> 970.83333 | P25: =N25-O25 -> 10679.167 | Q25: Resultat | R25: =L7 -> -31696.466
M26: Autres | N26: 40964.3 | O26: =(N26/18)*13 -> 29585.328 | P26: =N26-O26 -> 11378.972
M27: Immobilisations corporelles
M28: Materiel de bureau | N28: =20000+9000 -> 29000 | O28: =(N28/48)*13 -> 7854.1667 | P28: =N28-O28 -> 21145.833
M29: Materiel et outillage | N29: =2500+750+1200+2000+15000+25000 -> 46450 | O29: =(N29/24)*13 -> 25160.417 | P29: =N29-O29 -> 21289.583
M30: Materiel de transport | N30: 128000 | O30: =(N30/18)*13 -> 92444.444 | P30: =N30-O30 -> 35555.556
M31: Autres | N31: =5000+6000 -> 11000 | O31: =(5000/12)*12+(6000/12)*6 -> 8000 | P31: =N31-O31 -> 3000
M32: Immobilisations Financieres
M33: Loyer paye d'Avance | N33: 200000 | O33: =8333.33*14 -> 116666.62 | P33: =N33-O33 -> 83333.38
M34: Effet a recevoir | N34: 10000 | P34: 10000
M36: Actif Circulant | Q36: Dettes
M37: Stocks | N37: 238880 | P37: =N37 -> 238880 | Q37: Emprunt | R37: 0
M38: Disponibles | P38: =N41+N39+N40 -> 27234.4 | Q38: Dettes Fournisseurs | R38: 0
M39: Comptes Banques | N39: 1369 | Q39: Autres dettes | R39: 0
M40: Compte Lapoula | N40: 9880
M41: Caisse | N41: 15985.4
M42: Total Actif | N42: =SUM(N23:N39) -> 995708.77 | O42: =SUM(O23:O33) -> 367816.69 | P42: =SUM(P23:P38) -> 653757.48 | Q42: Total Passif | S42: =S21 -> 653757.48 | W42: =P42-S42 -> 8.333358e-06
S46: =P42-S42 -> 8.333358e-06
P49: =SUM(O23:O31) -> 251150.07
P50: =P49/8 -> 31393.759
M71: Part des associes au 31 Jan 2025
M72: Prnom & Nom | N72: Montant | O72: Pourcentage
M73: Hilaire BELLEVUE | N73: =N76-151038-115000 -> 817444.73 | O73: =N73/N76 -> 0.75446032
M74: Luckner JEAN | N74: 151038 | O74: =N74/N76 -> 0.13940047
M75: Nono ST-CYR | N75: 115000 | O75: =N75/N76 -> 0.10613921
M76: Total | N76: =L8 -> 1083482.7 | O76: =O73+O74+O75 -> 1

Sheet Fevrier 2025
B2: HLN Solutions | I2: HLN Solutions
B3: Etat de resultats | I3: Etat des capitaux propres
B4: Pour la periode terminant le 28 Fevrier 2025 | I4: Pour la periode terminant le 28 fevrier 2025
B5: VENTES BRUTES | E5: 32175 | I5: Capital initial | L5: 1083482.7
B6: Cout des Marchandises Vendues(CMV) | C6: 22367.5 | I6: Apports | L6: =38875+10000 -> 48875
B7: Cout des Produits Vendus | E7: =C6 -> 22367.5 | I7: Perte nette | L7: =E18 -> -69568.229
B8: MARGE BENEFICIAIRE BRUTE | E8: =E5-C6 -> 9807.5 | I8: Capital au 28 fevrier 2025 | L8: =SUM(L5:L7) -> 1062789.5
B9: Couts d'exploitation
B10: Salaires | C10: 25000
B11: Loyer | C11: ='[1]Tableau d''amortissement loyer'!$D$4 -> 8333.3333
B12: Publicite | C12: =(20802.71/12)+(40756/12)+(29040/12) -> 7549.8925
B13: Amortissements & Depreciations | C13: =25692.72 -> 25692.72
B14: Autres depenses | C14: =30000/12+11650/12+21750 -> 25220.833
B15: Total des couts d'Exploitation | E15: =SUM(C10:D14) -> 91796.779
B16: Perte nette | E16: =E8-E15 -> -81989.279
B17: Revenus hors activites | C17: =12000+421.05 -> 12421.05 | E17: =C17 -> 12421.05
B18: Resultat de la periode | E18: =E16+E17 -> -69568.229 | M18: Bilan
H19: =25000+1350+2690 -> 29040 | M19: Au 28 Fevrier 2025
M20: ACTIF | N20: Brut | O20: Amort/ Deprec | P20: Net | Q20: PASSIF
M21: Actif Immobilisé | Q21: Capitaux Propres | S21: =+R22+R25+R24 -> 711371.86
M22: Immobilisations incorporelles | Q22: Capital | R22: =L5+L6 -> 1132357.7
M23: Frais d'Etablissements | N23: =1250+10000+10518+1250+5500+20000+82292.65+41282.51+80302.31 -> 252395.47 | O23: =(N23/48)*14 -> 73615.345 | P23: =N23-O23 -> 178780.12 | Q23: Reserves | R23: 0
M24: Amenagements et decorations | N24: =15000+11000 -> 26000 | O24: =(N24/18)*14 -> 20222.222 | P24: =N24-O24 -> 5777.7778 | Q24: Report a nouveau | R24: =-386036.46-13500-27500-37359.67-88819.54+33613.94-29972.5+87532.4+56880.81+36807.67+9938.26+10872.6+15048.45-17021.9-80209.31+88728.66-421.05-10000 -> -351417.64
M25: Frais activation lapoula & impression | N25: =11650 -> 11650 | O25: =(N25/12)*2 -> 1941.6667 | P25: =N25-O25 -> 9708.3333 | Q25: Resultat | R25: =L7 -> -69568.229
M26: Autres | N26: 40964.3 | O26: =(N26/18)*14 -> 31861.122 | P26: =N26-O26 -> 9103.1778
M27: Immobilisations corporelles
M28: Materiel de bureau | N28: =20000+9000 -> 29000 | O28: =(N28/48)*14 -> 8458.3333 | P28: =N28-O28 -> 20541.667
M29: Materiel et outillage | N29: =2500+750+1200+2000+15000+25000 -> 46450 | O29: =(N29/24)*14 -> 27095.833 | P29: =N29-O29 -> 19354.167
M30: Materiel de transport | N30: 128000 | O30: =(N30/18)*14 -> 99555.556 | P30: =N30-O30 -> 28444.444
M31: Autres | N31: =(5000+6000+9695) -> 20695 | O31: =(5000/12)*13+(6000/12)*7+(9695/12)*1 -> 9724.5833 | P31: =N31-O31 -> 10970.417
M32: Immobilisations Financieres
M33: Loyer paye d'Avance | N33: 200000 | O33: =8333.33*15 -> 124999.95 | P33: =N33-O33 -> 75000.05
M34: Effet a recevoir | N34: 10000 | P34: 10000
M36: Actif Circulant | Q36: Dettes
M37: Stocks | N37: 318357.7 | P37: =N37 -> 318357.7 | Q37: Emprunt | R37: 0
M38: Disponibles | P38: =N41+N39+N40 -> 25334 | Q38: Dettes Fournisseurs | R38: 0
M39: Comptes Banques | N39: 1369 | Q39: Autres dettes | R39: 0
M40: Compte Lapoula | N40: 9880
M41: Caisse | N41: 14085
M42: Total Actif | N42: =SUM(N23:N39) -> 1084881.5 | O42: =SUM(O23:O33) -> 397474.61 | P42: =SUM(P23:P38) -> 711371.86 | Q42: Total Passif | S42: =S21 -> 711371.86 | W42: =P42-S42 -> -0.0029166667
S46: =P42-S42 -> -0.0029166667
P49: =SUM(O23:O31) -> 272474.66
P50: =P49/8 -> 34059.333
W59: Part des associes au 28 Fevrier 2025
W60: Prnom & Nom | X60: Montant | Y60: Pourcentage
W61: Hilaire BELLEVUE | X61: =X64-151038-140000 -> 841319.73 | Y61: =X61/X64 -> 0.74298052
W62: Luckner JEAN | X62: 151038 | Y62: =X62/X64 -> 0.13338364
W63: Nono ST-CYR | X63: =115000+25000 -> 140000 | Y63: =X63/X64 -> 0.12363584
W64: Total | X64: =R22 -> 1132357.7 | Y64: =Y61+Y62+Y63 -> 1

Sheet Mars 2025 
B2: HLN Solutions | I2: HLN Solutions
B3: Etat de resultats | I3: Etat des capitaux propres
B4: Pour la periode terminant le 31 Fevrier 2025 | I4: Pour la periode terminant le 31 Mars 2025
B5: VENTES BRUTES | E5: 43825 | I5: Capital initial | L5: 1062789.5
B6: Cout des Marchandises Vendues(CMV) | C6: 29255 | I6: Apports | L6: 10000
B7: Cout des Produits Vendus | E7: =C6 -> 29255 | I7: Perte nette | L7: =E18 -> -49641.299
B8: MARGE BENEFICIAIRE BRUTE | E8: =E5-C6 -> 14570 | I8: Capital au 28 fevrier 2025 | L8: =SUM(L5:L7) -> 1023148.2
B9: Couts d'exploitation
B10: Salaires | C10: 25000
B11: Loyer | C11: ='[1]Tableau d''amortissement loyer'!$D$4 -> 8333.3333
B12: Publicite | C12: =(20802.71/12)+(40756/12)+(29040/12) -> 7549.8925
B13: Amortissements & Depreciations | C13: =25692.72 -> 25692.72
B14: Autres depenses | C14: =30000/12+11650/12+6750 -> 10220.833
B15: Total des couts d'Exploitation | E15: =SUM(C10:D14) -> 76796.779
B16: Perte nette | E16: =E8-E15 -> -62226.779
B17: Revenus hors activites | C17: =12000+585.48 -> 12585.48 | E17: =C17 -> 12585.48
B18: Resultat de la periode | E18: =E16+E17 -> -49641.299 | M18: Bilan
H19: =25000+1350+2690 -> 29040 | M19: Au 31 mars 2025
M20: ACTIF | N20: Brut | O20: Amort/ Deprec | P20: Net | Q20: PASSIF
M21: Actif Immobilisé | Q21: Capitaux Propres | S21: =+R22+R25+R24 -> 725417.69
M22: Immobilisations incorporelles | Q22: Capital | R22: =L5+L6 -> 1072789.5
M23: Frais d'Etablissements | N23: =1250+10000+10518+1250+5500+20000+82292.65+41282.51+80302.31 -> 252395.47 | O23: =(N23/48)*15 -> 78873.584 | P23: =N23-O23 -> 173521.89 | Q23: Reserves | R23: 0
M24: Amenagements et decorations | N24: =15000+11000 -> 26000 | O24: =(N24/18)*15 -> 21666.667 | P24: =N24-O24 -> 4333.3333 | Q24: Report a nouveau | R24: =-386036.46-13500-27500-37359.67-88819.54+33613.94-29972.5+87532.4+56880.81+36807.67+9938.26+10872.6+15048.45-17021.9-80209.31+88728.66+43266.08 -> -297730.51
M25: Frais activation lapoula & impression | N25: =11650 -> 11650 | O25: =(N25/12)*3 -> 2912.5 | P25: =N25-O25 -> 8737.5 | Q25: Resultat | R25: =L7 -> -49641.299
M26: Autres | N26: 40964.3 | O26: =(N26/18)*15 -> 34136.917 | P26: =N26-O26 -> 6827.3833
M27: Immobilisations corporelles
M28: Materiel de bureau | N28: =20000+9000 -> 29000 | O28: =(N28/48)*15 -> 9062.5 | P28: =N28-O28 -> 19937.5
M29: Materiel et outillage | N29: =2500+750+1200+2000+15000+25000 -> 46450 | O29: =(N29/24)*15 -> 29031.25 | P29: =N29-O29 -> 17418.75
M30: Materiel de transport | N30: 128000 | O30: =(N30/18)*15 -> 106666.67 | P30: =N30-O30 -> 21333.333
M31: Autres | N31: =(5000+6000+9695) -> 20695 | O31: =(5000/12)*14+(6000/12)*8+(9695/12)*2 -> 11449.167 | P31: =N31-O31 -> 9245.8333
M32: Immobilisations Financieres
M33: Loyer paye d'Avance | N33: 200000 | O33: =8333.33*16 -> 133333.28 | P33: =N33-O33 -> 66666.72
M34: Effet a recevoir | N34: 10000 | P34: 10000
M36: Actif Circulant | Q36: Dettes
M37: Stocks | N37: 336615.65 | P37: =N37 -> 336615.65 | Q37: Emprunt | R37: 0
M38: Disponibles | P38: =N41+N39+N40 -> 50779.8 | Q38: Dettes Fournisseurs | R38: 0
M39: Comptes Banques | N39: 1369 | Q39: Autres dettes | R39: 0
M40: Compte Lapoula | N40: 1562.3
M41: Caisse | N41: 47848.5
M42: Total Actif | N42: =SUM(N23:N39) -> 1103139.4 | O42: =SUM(O23:O33) -> 427132.53 | P42: =SUM(P23:P38) -> 725417.69 | Q42: Total Passif | S42: =S21 -> 725417.69 | W42: =P42-S42 -> -0.0018750001
S46: =P42-S42 -> -0.0018750001
P49: =SUM(O23:O31) -> 293799.25
P50: =P49/8 -> 36724.906
W59: Part des associes au 28 Fevrier 2025
W60: Prnom & Nom | X60: Montant | Y60: Pourcentage
W61: Hilaire BELLEVUE | X61: =X64-151038-140000 -> 781751.5 | Y61: =X61/X64 -> 0.72870913
W62: Luckner JEAN | X62: 151038 | Y62: =X62/X64 -> 0.14078997
W63: Nono ST-CYR | X63: =115000+25000 -> 140000 | Y63: =X63/X64 -> 0.1305009
W64: Total | X64: =R22 -> 1072789.5 | Y64: =Y61+Y62+Y63 -> 1

Sheet Avril 2025
B2: HLN Solutions | I2: HLN Solutions
B3: Etat de resultats | I3: Etat des capitaux propres
B4: Pour la periode terminant le 30 Avril 2025 | I4: Pour la periode terminant le 30 Avril 2025
B5: VENTES BRUTES | E5: 71850 | I5: Capital initial | L5: ='Mars 2025 '!L8 -> 1023148.2
B6: Cout des Marchandises Vendues(CMV) | C6: 48270.69 | I6: Apports | L6: 10000
B7: Cout des Produits Vendus | E7: =C6 -> 48270.69 | I7: Perte nette | L7: =E18 -> -60130.809
B8: MARGE BENEFICIAIRE BRUTE | E8: =E5-C6 -> 23579.31 | I8: Capital au 30 Avril 2025 | L8: =SUM(L5:L7) -> 973017.39
B9: Couts d'exploitation
B10: Salaires | C10: 25000
B11: Loyer | C11: ='[1]Tableau d''amortissement loyer'!$D$4 -> 8333.3333
B12: Publicite | C12: =(20802.71/12)+(40756/12)+(29040/12) -> 7549.8925
B13: Amortissements & Depreciations | C13: =25692.72 -> 25692.72
B14: Autres depenses | C14: =30000/12+11650/12+26320 -> 29790.833
B15: Total des couts d'Exploitation | E15: =SUM(C10:D14) -> 96366.779
B16: Perte nette | E16: =E8-E15 -> -72787.469
B17: Revenus hors activites | C17: =12000+656.66 -> 12656.66 | E17: =C17 -> 12656.66
B18: Resultat de la periode | E18: =E16+E17 -> -60130.809 | M18: Bilan
H19: =25000+1350+2690 -> 29040 | M19: Au 30 Avril 2025
M20: ACTIF | N20: Brut | O20: Amort/ Deprec | P20: Net | Q20: PASSIF
M21: Actif Immobilisé | Q21: Capitaux Propres | S21: =+R22+R25+R24 -> 687562.7
M22: Immobilisations incorporelles | Q22: Capital | R22: =L5+L6 -> 1033148.2
M23: Frais d'Etablissements | N23: =1250+10000+10518+1250+5500+20000+82292.65+41282.51+80302.31 -> 252395.47 | O23: =(N23/48)*16 -> 84131.823 | P23: =N23-O23 -> 168263.65 | Q23: Reserves | R23: 0
M24: Amenagements et decorations | N24: =15000+11000 -> 26000 | O24: =(N24/18)*16 -> 23111.111 | P24: =N24-O24 -> 2888.8889 | Q24: Report a nouveau | R24: =-386036.46-13500-27500-37359.67-88819.54+33613.94-29972.5+87532.4+56880.81+36807.67+9938.26+10872.6+15048.45-17021.9-80209.31+88728.66+43266.08+12275.82 -> -285454.69
M25: Frais activation lapoula & impression | N25: =11650 -> 11650 | O25: =(N25/12)*4 -> 3883.3333 | P25: =N25-O25 -> 7766.6667 | Q25: Resultat | R25: =L7 -> -60130.809
M26: Autres | N26: 40964.3 | O26: =(N26/18)*16 -> 36412.711 | P26: =N26-O26 -> 4551.5889
M27: Immobilisations corporelles
M28: Materiel de bureau | N28: =20000+9000 -> 29000 | O28: =(N28/48)*16 -> 9666.6667 | P28: =N28-O28 -> 19333.333
M29: Materiel et outillage | N29: =2500+750+1200+2000+15000+25000 -> 46450 | O29: =(N29/24)*16 -> 30966.667 | P29: =N29-O29 -> 15483.333
M30: Materiel de transport | N30: 128000 | O30: =(N30/18)*16 -> 113777.78 | P30: =N30-O30 -> 14222.222
M31: Autres | N31: =(5000+6000+9695) -> 20695 | O31: =(6000/12)*8+(9695/12)*2 -> 5615.8333 | P31: =N31-O31 -> 15079.167
M32: Immobilisations Financieres
M33: Loyer paye d'Avance | N33: 200000 | O33: =8333.33*17 -> 141666.61 | P33: =N33-O33 -> 58333.39
M34: Effet a recevoir | N34: 10000 | P34: 10000
M36: Actif Circulant | Q36: Dettes
M37: Stocks | N37: 311748.5 | P37: =N37 -> 311748.5 | Q37: Emprunt | R37: 0
M38: Disponibles | P38: =N41+N39+N40 -> 59891.96 | Q38: Dettes Fournisseurs | R38: 0
M39: Comptes Banques | N39: 1369 | Q39: Autres dettes | R39: 0
M40: Compte Lapoula | N40: 10252.27
M41: Caisse | N41: 48270.69
M42: Total Actif | N42: =SUM(N23:N39) -> 1078272.3 | O42: =SUM(O23:O33) -> 449232.53 | P42: =SUM(P23:P38) -> 687562.7 | Q42: Total Passif | S42: =S21 -> 687562.7 | W42: =P42-S42 -> -0.005
S46: =P42-S42 -> -0.005
P49: =SUM(O23:O31) -> 307565.92
P50: =P49/8 -> 38445.74
W59: Part des associes au 28 Fevrier 2025
W60: Prnom & Nom | X60: Montant | Y60: Pourcentage
W61: Hilaire BELLEVUE | X61: =X64-151038-140000 -> 742110.2 | Y61: =X61/X64 -> 0.71829985
W62: Luckner JEAN | X62: 151038 | Y62: =X62/X64 -> 0.146192
W63: Nono ST-CYR | X63: =115000+25000 -> 140000 | Y63: =X63/X64 -> 0.13550815
W64: Total | X64: =R22 -> 1033148.2 | Y64: =Y61+Y62+Y63 -> 1

Sheet Mai 2025
B2: HLN Solutions | I2: HLN Solutions
B3: Etat de resultats | I3: Etat des capitaux propres
B4: Pour la periode terminant le 31 Mai 2025 | I4: Pour la periode terminant le 31 Mai 2025
B5: VENTES BRUTES | E5: 65625 | I5: Capital initial | L5: ='Avril 2025'!L8 -> 973017.39
B6: Cout des Marchandises Vendues(CMV) | C6: 47661.54 | I6: Apports | L6: 0
B7: Cout des Produits Vendus | E7: =C6 -> 47661.54 | I7: Perte nette | L7: =E18 -> -31681.209
B8: MARGE BENEFICIAIRE BRUTE | E8: =E5-C6 -> 17963.46 | I8: Capital au 30 Avril 2025 | L8: =SUM(L5:L7) -> 941336.18
B9: Couts d'exploitation
B10: Salaires | C10: 15000
B11: Loyer | C11: ='[1]Tableau d''amortissement loyer'!$D$4 -> 8333.3333
B12: Publicite | C12: =(20802.71/12)+(40756/12)+(29040/12) -> 7549.8925
B13: Amortissements & Depreciations | C13: =25692.72 -> 25692.72
B14: Autres depenses | C14: =30000/12+11650/12+2350 -> 5820.8333
B15: Total des couts d'Exploitation | E15: =SUM(C10:D14) -> 62396.779
B16: Perte nette | E16: =E8-E15 -> -44433.319
B17: Revenus hors activites | C17: =12000+752.11 -> 12752.11 | E17: =C17 -> 12752.11
B18: Resultat de la periode | E18: =E16+E17 -> -31681.209 | M18: Bilan
H19: =25000+1350+2690 -> 29040 | M19: Au 31 Mai 2025
M20: ACTIF | N20: Brut | O20: Amort/ Deprec | P20: Net | Q20: PASSIF
M21: Actif Immobilisé | Q21: Capitaux Propres | S21: =+R22+R25+R24 -> 707878.64
M22: Immobilisations incorporelles | Q22: Capital | R22: =L5+L6 -> 973017.39
M23: Frais d'Etablissements | N23: =1250+10000+10518+1250+5500+20000+82292.65+41282.51+80302.31 -> 252395.47 | O23: =(N23/48)*17 -> 89390.062 | P23: =N23-O23 -> 163005.41 | Q23: Reserves | R23: 0
M24: Amenagements et decorations | N24: =15000+11000 -> 26000 | O24: =(N24/18)*17 -> 24555.556 | P24: =N24-O24 -> 1444.4444 | Q24: Report a nouveau | R24: =-386036.46-13500-27500-37359.67-88819.54+33613.94-29972.5+87532.4+56880.81+36807.67+9938.26+10872.6+15048.45-17021.9-80209.31+88728.66+107539.05 -> -233457.54
M25: Frais activation lapoula & impression | N25: =11650 -> 11650 | O25: =(N25/12)*5 -> 4854.1667 | P25: =N25-O25 -> 6795.8333 | Q25: Resultat | R25: =L7 -> -31681.209
M26: Autres | N26: 40964.3 | O26: =(N26/18)*17 -> 38688.506 | P26: =N26-O26 -> 2275.7944
M27: Immobilisations corporelles
M28: Materiel de bureau | N28: =20000+9000 -> 29000 | O28: =(N28/48)*17 -> 10270.833 | P28: =N28-O28 -> 18729.167
M29: Materiel et outillage | N29: =2500+750+1200+2000+15000+25000 -> 46450 | O29: =(N29/24)*17 -> 32902.083 | P29: =N29-O29 -> 13547.917
M30: Materiel de transport | N30: 128000 | O30: =(N30/18)*17 -> 120888.89 | P30: =N30-O30 -> 7111.1111
M31: Autres | N31: =(5000+6000+9695) -> 20695 | O31: =(6000/12)*9+(9695/12)*3 -> 6923.75 | P31: =N31-O31 -> 13771.25
M32: Immobilisations Financieres
M33: Loyer paye d'Avance | N33: 200000 | O33: =8333.33*18 -> 149999.94 | P33: =N33-O33 -> 50000.06
M34: Effet a recevoir | N34: 10000 | P34: 10000
M36: Actif Circulant | Q36: Dettes
M37: Stocks | N37: 335283.5 | P37: =N37 -> 335283.5 | Q37: Emprunt | R37: 0
M38: Disponibles | P38: =N41+N39+N40 -> 85914.16 | Q38: Dettes Fournisseurs | R38: 0
M39: Comptes Banques | N39: 1369 | Q39: Autres dettes | R39: 0
M40: Compte Lapoula | N40: 1175
M41: Caisse | N41: 83370.16
M42: Total Actif | N42: =SUM(N23:N39) -> 1101807.3 | O42: =SUM(O23:O33) -> 478473.79 | P42: =SUM(P23:P38) -> 707878.64 | Q42: Total Passif | S42: =S21 -> 707878.64 | W42: =P42-S42 -> 0.0018750002
S46: =P42-S42 -> 0.0018750002
P49: =SUM(O23:O31) -> 328473.85
P50: =P49/8 -> 41059.231
W59: Part des associes au 28 Fevrier 2025
W60: Prnom & Nom | X60: Montant | Y60: Pourcentage
W61: Hilaire BELLEVUE | X61: =X64-151038-140000 -> 681979.39 | Y61: =X61/X64 -> 0.70089127
W62: Luckner JEAN | X62: 151038 | Y62: =X62/X64 -> 0.15522641
W63: Nono ST-CYR | X63: =115000+25000 -> 140000 | Y63: =X63/X64 -> 0.14388232
W64: Total | X64: =R22 -> 973017.39 | Y64: =Y61+Y62+Y63 -> 1

Sheet Juin 2025
B2: HLN Solutions | I2: HLN Solutions
B3: Etat de resultats | I3: Etat des capitaux propres
B4: Pour la periode terminant le 30 Juin 2025 | I4: Pour la periode terminant le 30 Juin 2025
B5: VENTES BRUTES | E5: 74150 | I5: Capital initial | L5: ='Mai 2025'!L8 -> 941336.18
B6: Cout des Marchandises Vendues(CMV) | C6: 54952.45 | I6: Apports | L6: 0
B7: Cout des Produits Vendus | E7: =C6 -> 54952.45 | I7: Perte nette | L7: =E18 -> -28993.669
B8: MARGE BENEFICIAIRE BRUTE | E8: =E5-C6 -> 19197.55 | I8: Capital au 30 Juin 2025 | L8: =SUM(L5:L7) -> 912342.51
B9: Couts d'exploitation
B10: Salaires | C10: 15000
B11: Loyer | C11: ='[1]Tableau d''amortissement loyer'!$D$4 -> 8333.3333
B12: Publicite | C12: =(20802.71/12)+(40756/12)+(29040/12) -> 7549.8925
B13: Amortissements & Depreciations | C13: =25692.72 -> 25692.72
B14: Autres depenses | C14: =30000/12+11650/12+950 -> 4420.8333
B15: Total des couts d'Exploitation | E15: =SUM(C10:D14) -> 60996.779
B16: Perte nette | E16: =E8-E15 -> -41799.229
B17: Revenus hors activites | C17: =12000+805.56 -> 12805.56 | E17: =C17 -> 12805.56
B18: Resultat de la periode | E18: =E16+E17 -> -28993.669 | M18: Bilan
H19: =25000+1350+2690 -> 29040 | M19: Au 30 Juin 2025
M20: ACTIF | N20: Brut | O20: Amort/ Deprec | P20: Net | Q20: PASSIF
M21: Actif Immobilisé | Q21: Capitaux Propres | S21: =+R22+R25+R24 -> 710532.86
M22: Immobilisations incorporelles | Q22: Capital | R22: =L5+L6 -> 941336.18
M23: Frais d'Etablissements | N23: =1250+10000+10518+1250+5500+20000+82292.65+41282.51+80302.31 -> 252395.47 | O23: =(N23/48)*18 -> 94648.301 | P23: =N23-O23 -> 157747.17 | Q23: Reserves | R23: 0
F24: =154375.72-805.56 -> 153570.16 | M24: Amenagements et decorations | N24: =15000+11000 -> 26000 | O24: =(N24/18)*18 -> 26000 | P24: =N24-O24 -> 0 | Q24: Report a nouveau | R24: =-386036.46-13500-27500-37359.67-88819.54+33613.94-29972.5+87532.4+56880.81+36807.67+9938.26+10872.6+15048.45-17021.9-80209.31+88728.66+107539.05+32453.45-805.56 -> -201809.65
M25: Frais activation lapoula & impression | N25: =11650 -> 11650 | O25: =(N25/12)*6 -> 5825 | P25: =N25-O25 -> 5825 | Q25: Resultat | R25: =L7 -> -28993.669
M26: Autres | N26: 40964.3 | O26: =(N26/18)*18 -> 40964.3 | P26: =N26-O26 -> 0
M27: Immobilisations corporelles
M28: Materiel de bureau | N28: =20000+9000 -> 29000 | O28: =(N28/48)*18 -> 10875 | P28: =N28-O28 -> 18125
M29: Materiel et outillage | N29: =2500+750+1200+2000+15000+25000 -> 46450 | O29: =(N29/24)*18 -> 34837.5 | P29: =N29-O29 -> 11612.5
M30: Materiel de transport | N30: 128000 | O30: =(N30/18)*18 -> 128000 | P30: =N30-O30 -> 0
M31: Autres | N31: =(5000+6000+9695) -> 20695 | O31: =(6000/12)*10+(9695/12)*4 -> 8231.6667 | P31: =N31-O31 -> 12463.333
M32: Immobilisations Financieres
M33: Loyer paye d'Avance | N33: 200000 | O33: =8333.33*19 -> 158333.27 | P33: =N33-O33 -> 41666.73
M34: Effet a recevoir | N34: 10000 | P34: 10000
M36: Actif Circulant | Q36: Dettes
M37: Stocks | N37: 280612.17 | P37: =N37 -> 280612.17 | Q37: Emprunt | R37: 0
M38: Disponibles | P38: =N41+N39+N40 -> 172480.96 | Q38: Dettes Fournisseurs | R38: 0
M39: Comptes Banques | N39: 1369 | Q39: Autres dettes | R39: 0
M40: Compte Lapoula | N40: 17541.8
M41: Caisse | N41: =154375.72-805.56 -> 153570.16
M42: Total Actif | N42: =SUM(N23:N39) -> 1047135.9 | O42: =SUM(O23:O33) -> 507715.04 | P42: =SUM(P23:P38) -> 710532.86 | Q42: Total Passif | S42: =S21 -> 710532.86 | W42: =P42-S42 -> -0.00125
S46: =P42-S42 -> -0.00125
P49: =SUM(O23:O31) -> 349381.77
P50: =P49/8 -> 43672.721
W59: Part des associes au 28 Fevrier 2025
W60: Prnom & Nom | X60: Montant | Y60: Pourcentage
W61: Hilaire BELLEVUE | X61: =X64-151038-140000 -> 650298.18 | Y61: =X61/X64 -> 0.69082459
W62: Luckner JEAN | X62: 151038 | Y62: =X62/X64 -> 0.16045065
W63: Nono ST-CYR | X63: =115000+25000 -> 140000 | Y63: =X63/X64 -> 0.14872476
W64: Total | X64: =R22 -> 941336.18 | Y64: =Y61+Y62+Y63 -> 1

Sheet Juill 2025
B2: HLN Solutions | I2: HLN Solutions
B3: Etat des résultats | I3: Etat des capitaux propres
B4: Pour la periode terminant le 31 Juillet 2025 | I4: Pour la période terminant le 31 Juillet 2025
B5: VENTES BRUTES | E5: 52175 | I5: Capital initial | L5: ='Juin 2025'!L8 -> 912342.51
B6: Cout des Marchandises Vendues(CMV) | C6: 41383.3 | I6: Apports | L6: 0
B7: Cout des Produits Vendus | E7: =C6 -> 41383.3 | I7: Perte nette | L7: =E18 -> -22577.846
B8: MARGE BENEFICIAIRE BRUTE | E8: =E5-C6 -> 10791.7 | I8: Capital au 31 Juillet 2025 | L8: =SUM(L5:L7) -> 889764.67
B9: Couts d'exploitation
B10: Salaires | C10: 15000
B11: Loyer | C11: ='[1]Tableau d''amortissement loyer'!$D$4 -> 8333.3333
B12: Publicite | C12: =(20802.71/12)+(29040/12) -> 4153.5592
B13: Amortissements & Depreciations | C13: =25692.72-2275.79-7111.11 -> 16305.82
B14: Autres depenses | C14: =30000/12+11650/12 -> 3470.8333
B15: Total des couts d'Exploitation | E15: =SUM(C10:D14) -> 47263.546
B16: Perte nette | E16: =E8-E15 -> -36471.846
B17: Revenus hors activites | C17: =9000+4894 -> 13894 | E17: =C17 -> 13894
B18: Resultat de la periode | E18: =E16+E17 -> -22577.846 | M18: Bilan
M19: Au 31 Juillet 2025
M20: ACTIF | N20: Brut | O20: Amort/ Deprec | P20: Net | Q20: PASSIF
M21: Actif Immobilisé | Q21: Capitaux Propres | S21: =+R22+R25+R24 -> 731851.7
M22: Immobilisations incorporelles | Q22: Capital | R22: =L5+L6 -> 912342.51
M23: Frais d'Etablissements | N23: =1250+10000+10518+1250+5500+20000+82292.65+41282.51+80302.31 -> 252395.47 | O23: =(N23/48)*19 -> 99906.54 | P23: =N23-O23 -> 152488.93 | Q23: Reserves | R23: 0
M24: Amenagements et decorations | N24: =15000+11000 -> 26000 | O24: =(N24/18)*18 -> 26000 | P24: =N24-O24 -> 0 | Q24: Report a nouveau | R24: =-386036.46-13500-27500-37359.67-88819.54+33613.94-29972.5+87532.4+56880.81+36807.67+9938.26+10872.6+15048.45-17021.9-80209.31+88728.66+107539.05+32453.45-805.56+43896.68 -> -157912.97
M25: Frais activation lapoula & impression | N25: =11650 -> 11650 | O25: =(N25/12)*7 -> 6795.8333 | P25: =N25-O25 -> 4854.1667 | Q25: Resultat | R25: =L7 -> -22577.846
M26: Autres | N26: 40964.3 | O26: =(N26/18)*18 -> 40964.3 | P26: =N26-O26 -> 0
M27: Immobilisations corporelles
M28: Materiel de bureau | N28: =20000+9000 -> 29000 | O28: =(N28/48)*19 -> 11479.167 | P28: =N28-O28 -> 17520.833
M29: Materiel et outillage | N29: =2500+750+1200+2000+15000+25000 -> 46450 | O29: =(N29/24)*19 -> 36772.917 | P29: =N29-O29 -> 9677.0833
M30: Materiel de transport | N30: 128000 | O30: =(N30/18)*18 -> 128000 | P30: =N30-O30 -> 0
M31: Autres | N31: =(5000+6000+9695) -> 20695 | O31: =(6000/12)*11+(9695/12)*5 -> 9539.5833 | P31: =N31-O31 -> 11155.417
M32: Immobilisations Financieres
M33: Loyer paye d'Avance | N33: 200000 | O33: =8333.33*14 -> 116666.62 | P33: =N33-O33 -> 83333.38
M34: Effet a recevoir | N34: 10000 | P34: 10000
M36: Actif Circulant | Q36: Dettes
M37: Stocks | N37: 239228.89 | P37: =N37 -> 239228.89 | Q37: Emprunt | R37: 0
M38: Disponibles | P38: =N41+N39+N40 -> 203593 | Q38: Dettes Fournisseurs | R38: 0
M39: Comptes Banques | N39: 1369 | Q39: Autres dettes | R39: 0
M40: Compte Lapoula | N40: 13854
M41: Caisse | N41: 188370
M42: Total Actif | N42: =SUM(N23:N39) -> 1005752.7 | O42: =SUM(O23:O33) -> 476124.96 | P42: =SUM(P23:P38) -> 731851.7 | Q42: Total Passif | S42: =S21 -> 731851.7 | W42: =P42-S42 -> 0.0022916668
S46: =P42-S42 -> 0.0022916668
P49: =SUM(O23:O31) -> 359458.34
P50: =P49/8 -> 44932.293
W59: Part des associes au 28 Fevrier 2025
W60: Prnom & Nom | X60: Montant | Y60: Pourcentage
W61: Hilaire BELLEVUE | X61: =X64-151038-140000 -> 621304.51 | Y61: =X61/X64 -> 0.68099919
W62: Luckner JEAN | X62: 151038 | Y62: =X62/X64 -> 0.16554967
W63: Nono ST-CYR | X63: =115000+25000 -> 140000 | Y63: =X63/X64 -> 0.15345114
W64: Total | X64: =R22 -> 912342.51 | Y64: =Y61+Y62+Y63 -> 1

Sheet Aout 2025
B2: HLN Solutions | I2: HLN Solutions
B3: Etat des résultats | I3: Etat des capitaux propres
B4: Pour la periode terminant le 31 Aout 2025 | I4: Pour la période terminant le 31 Aout 2025
B5: VENTES BRUTES | E5: 39525 | I5: Capital initial | L5: ='Juill 2025'!L8 -> 889764.67
B6: Cout des Marchandises Vendues(CMV) | C6: 29895.04 | I6: Apports | L6: 0
B7: Cout des Produits Vendus | E7: =C6 -> 29895.04 | I7: Perte nette | L7: =E18 -> -33282.586
B8: MARGE BENEFICIAIRE BRUTE | E8: =E5-C6 -> 9629.96 | I8: Capital au 31 Aout 2025 | L8: =SUM(L5:L7) -> 856482.08
B9: Couts d'exploitation
B10: Salaires | C10: 15000
B11: Loyer | C11: ='[1]Tableau d''amortissement loyer'!$D$4 -> 8333.3333
B12: Publicite | C12: =(20802.71/12)+(29040/12) -> 4153.5592
B13: Amortissements & Depreciations | C13: =25692.72-2275.79-7111.11 -> 16305.82
B14: Autres depenses | C14: =11650/12 -> 970.83333
B15: Total des couts d'Exploitation | E15: =SUM(C10:D14) -> 44763.546
B16: Perte nette | E16: =E8-E15 -> -35133.586
B17: Revenus hors activites | C17: =1851 -> 1851 | E17: =C17 -> 1851
B18: Resultat de la periode | E18: =E16+E17 -> -33282.586 | M18: Bilan
M19: Au 31 Aout 2025
M20: ACTIF | N20: Brut | O20: Amort/ Deprec | P20: Net | Q20: PASSIF
M21: Actif Immobilisé | Q21: Capitaux Propres | S21: =+R22+R25+R24 -> 710286.12
M22: Immobilisations incorporelles | Q22: Capital | R22: =L5+L6 -> 889764.67
M23: Frais d'Etablissements | N23: =1250+10000+10518+1250+5500+20000+82292.65+41282.51+80302.31 -> 252395.47 | O23: =(N23/48)*20 -> 105164.78 | P23: =N23-O23 -> 147230.69 | Q23: Reserves | R23: 0
M24: Amenagements et decorations | N24: =15000+11000 -> 26000 | O24: =(N24/18)*18 -> 26000 | P24: =N24-O24 -> 0 | Q24: Report a nouveau | R24: =-386036.46-13500-27500-37359.67-88819.54+33613.94-29972.5+87532.4+56880.81+36807.67+9938.26+10872.6+15048.45-17021.9-80209.31+88728.66+107539.05+32453.45-805.56+43896.68+11717.01 -> -146195.96
M25: Frais activation lapoula & impression | N25: =11650 -> 11650 | O25: =(N25/12)*8 -> 7766.6667 | P25: =N25-O25 -> 3883.3333 | Q25: Resultat | R25: =L7 -> -33282.586
M26: Autres | N26: 40964.3 | O26: =(N26/18)*18 -> 40964.3 | P26: =N26-O26 -> 0
M27: Immobilisations corporelles
M28: Materiel de bureau | N28: =20000+9000 -> 29000 | O28: =(N28/48)*20 -> 12083.333 | P28: =N28-O28 -> 16916.667
M29: Materiel et outillage | N29: =2500+750+1200+2000+15000+25000 -> 46450 | O29: =(N29/24)*20 -> 38708.333 | P29: =N29-O29 -> 7741.6667
M30: Materiel de transport | N30: 128000 | O30: =(N30/18)*18 -> 128000 | P30: =N30-O30 -> 0
M31: Autres | N31: =(5000+6000+9695) -> 20695 | O31: =(6000/12)*12+(9695/12)*6 -> 10847.5 | P31: =N31-O31 -> 9847.5
M32: Immobilisations Financieres
M33: Loyer paye d'Avance | N33: 200000 | O33: =8333.33*15 -> 124999.95 | P33: =N33-O33 -> 75000.05
M34: Effet a recevoir | N34: =10000+6000 -> 16000 | P34: =N34 -> 16000
M36: Actif Circulant | Q36: Dettes
M37: Stocks | N37: 258949.91 | P37: =N37 -> 258949.91 | Q37: Emprunt | R37: 0
M38: Disponibles | P38: =N41+N39+N40 -> 174716.3 | Q38: Dettes Fournisseurs | R38: 0
M39: Comptes Banques | N39: 1369 | Q39: Autres dettes | R39: 0
M40: Compte Lapoula | N40: 20452.3
M41: Caisse | N41: 152895
M42: Total Actif | N42: =SUM(N23:N39) -> 1031473.7 | O42: =SUM(O23:O33) -> 494534.86 | P42: =SUM(P23:P38) -> 710286.12 | Q42: Total Passif | S42: =S21 -> 710286.12 | W42: =P42-S42 -> -0.0041666667
S46: =P42-S42 -> -0.0041666667
P49: =SUM(O23:O31) -> 369534.91
P50: =P49/8 -> 46191.864
W59: Part des associes au 28 Fevrier 2025
W60: Prnom & Nom | X60: Montant | Y60: Pourcentage
W61: Hilaire BELLEVUE | X61: =X64-151038-140000 -> 598726.67 | Y61: =X61/X64 -> 0.67290452
W62: Luckner JEAN | X62: 151038 | Y62: =X62/X64 -> 0.1697505
W63: Nono ST-CYR | X63: =115000+25000 -> 140000 | Y63: =X63/X64 -> 0.15734498
W64: Total | X64: =R22 -> 889764.67 | Y64: =Y61+Y62+Y63 -> 1

Sheet Sept 2025 
B2: HLN Solutions | I2: HLN Solutions
B3: Etat des résultats | I3: Etat des capitaux propres
B4: Pour la periode terminant le 30 Sept 2025 | I4: Pour la période terminant le 30 Sept 2025
B5: VENTES BRUTES | E5: 33450 | I5: Capital initial | L5: 856482.08
B6: Cout des Marchandises Vendues(CMV) | C6: 25410 | I6: Apports | L6: 0
B7: Cout des Produits Vendus | E7: =C6 -> 25410 | I7: Perte nette | L7: =E18 -> -31723.546
B8: MARGE BENEFICIAIRE BRUTE | E8: =E5-C6 -> 8040 | I8: Capital au 30 Sept 2025 | L8: =SUM(L5:L7) -> 824758.53
B9: Couts d'exploitation
B10: Salaires | C10: 15000
B11: Loyer | C11: ='[1]Tableau d''amortissement loyer'!$D$4 -> 8333.3333
B12: Publicité | C12: =(20802.71/12)+(29040/12) -> 4153.5592
B13: Amortissements & Dépréciations | C13: =25692.72-2275.79-7111.11 -> 16305.82
B14: Autres depenses | C14: =11650/12 -> 970.83333
B15: Total des couts d'Exploitation | E15: =SUM(C10:D14) -> 44763.546
B16: Perte nette | E16: =E8-E15 -> -36723.546
B17: Revenus hors activites | C17: =5000 -> 5000 | E17: =C17 -> 5000
B18: Résultat de la période | E18: =E16+E17 -> -31723.546 | M18: Bilan
M19: Au 30 Sept 2025
M20: ACTIF | N20: Brut | O20: Amort/ Deprec | P20: Net | Q20: PASSIF
M21: Actif Immobilisé | Q21: Capitaux Propres | S21: =+R22+R25+R24 -> 638714.64
M22: Immobilisations incorporelles | Q22: Capital | R22: =L5+L6 -> 856482.08
M23: Frais d'Etablissements | N23: =1250+10000+10518+1250+5500+20000+82292.65+41282.51+80302.31 -> 252395.47 | O23: =(N23/48)*21 -> 110423.02 | P23: =N23-O23 -> 141972.45 | Q23: Reserves | R23: 0
M24: Amenagements et decorations | N24: =15000+11000 -> 26000 | O24: =(N24/18)*18 -> 26000 | P24: =N24-O24 -> 0 | Q24: Report a nouveau | R24: =-386036.46-13500-27500-37359.67-88819.54+33613.94-29972.5+87532.4+56880.81+36807.67+9938.26+10872.6+15048.45-17021.9-80209.31+88728.66+107539.05+32453.45-805.56+43896.68+11717.01-39847.93 -> -186043.89
M25: Frais activation lapoula & impression | N25: =11650 -> 11650 | O25: =(N25/12)*9 -> 8737.5 | P25: =N25-O25 -> 2912.5 | Q25: Resultat | R25: =L7 -> -31723.546
M26: Autres | N26: 40964.3 | O26: =(N26/18)*18 -> 40964.3 | P26: =N26-O26 -> 0
M27: Immobilisations corporelles
M28: Materiel de bureau | N28: =20000+9000 -> 29000 | O28: =(N28/48)*21 -> 12687.5 | P28: =N28-O28 -> 16312.5
M29: Materiel et outillage | N29: =2500+750+1200+2000+15000+25000 -> 46450 | O29: =(N29/24)*21 -> 40643.75 | P29: =N29-O29 -> 5806.25
M30: Materiel de transport | N30: 128000 | O30: =(N30/18)*18 -> 128000 | P30: =N30-O30 -> 0
M31: Autres | N31: =(5000+6000+9695) -> 20695 | O31: =(6000/12)*12+(9695/12)*7 -> 11655.417 | P31: =N31-O31 -> 9039.5833
M32: Immobilisations Financieres
M33: Loyer paye d'Avance | N33: 200000 | O33: =8333.33*22 -> 183333.26 | P33: =N33-O33 -> 16666.74
M34: Effet a recevoir | N34: =10000+6000 -> 16000 | P34: =N34 -> 16000
M36: Actif Circulant | Q36: Dettes
M37: Stocks | N37: =#REF! -> #REF! | P37: =N37 -> #REF! | Q37: Emprunt | R37: 0
M38: Disponibles | P38: =N41+N39+N40 -> #REF! | Q38: Dettes Fournisseurs | R38: 0
M39: Comptes Banques | N39: 1369 | Q39: Autres dettes | R39: 0
M40: Compte Lapoula | N40: =#REF! -> #REF!
M41: Caisse | N41: =#REF! -> #REF!
M42: Total Actif | N42: =SUM(N23:N39) -> #REF! | O42: =SUM(O23:O33) -> 562444.74 | P42: =SUM(P23:P38) -> #REF! | Q42: Total Passif | S42: =S21 -> 638714.64 | W42: =P42-S42 -> #REF!
S46: =P42-S42 -> #REF!
P49: =SUM(O23:O31) -> 379111.48
P50: =P49/8 -> 47388.936
W59: Part des associes au 28 Fevrier 2025
W60: Prnom & Nom | X60: Montant | Y60: Pourcentage
W61: Hilaire BELLEVUE | X61: =X64-151038-140000 -> 565444.08 | Y61: =X61/X64 -> 0.66019371
W62: Luckner JEAN | X62: 151038 | Y62: =X62/X64 -> 0.17634695
W63: Nono ST-CYR | X63: =115000+25000 -> 140000 | Y63: =X63/X64 -> 0.16345935
W64: Total | X64: =R22 -> 856482.08 | Y64: =Y61+Y62+Y63 -> 1

Sheet OCT 2025
B2: HLN Solutions | I2: HLN Solutions
B3: Etat des résultats | I3: Etat des capitaux propres
B4: Pour la periode terminant le 31 Oct 2025 | I4: Pour la période terminant le 31 Oct 2025
B5: VENTES BRUTES | E5: 49600 | I5: Capital initial | L5: ='Sept 2025 '!L8 -> 824758.53
B6: Cout des Marchandises Vendues(CMV) | C6: 35384.95 | I6: Apports | L6: 0
B7: Cout des Produits Vendus | E7: =C6 -> 35384.95 | I7: Perte nette | L7: =E18 -> -26388.286
B8: MARGE BENEFICIAIRE BRUTE | E8: =E5-C6 -> 14215.05 | I8: Capital au 31 Oct 2025 | L8: =SUM(L5:L7) -> 798370.25
B9: Couts d'exploitation
B10: Salaires | C10: 15000
B11: Loyer | C11: ='[1]Tableau d''amortissement loyer'!$D$4 -> 8333.3333
B12: Publicité | C12: =(20802.71/12)+(29040/12) -> 4153.5592
B13: Amortissements & Dépréciations | C13: =25692.72-2275.79-7111.11 -> 16305.82
B14: Autres depenses | C14: =11650/12+1300 -> 2270.8333
B15: Total des couts d'Exploitation | E15: =SUM(C10:D14) -> 46063.546
B16: Perte nette | E16: =E8-E15 -> -31848.496
B17: Revenus hors activites | C17: =2610.21+2850 -> 5460.21 | E17: =C17 -> 5460.21
B18: Résultat de la période | E18: =E16+E17 -> -26388.286 | M18: Bilan
M19: Au 31 Oct 2025
M20: ACTIF | N20: Brut | O20: Amort/ Deprec | P20: Net | Q20: PASSIF
M21: Actif Immobilisé | Q21: Capitaux Propres | S21: =+R22+R25+R24 -> 604554.17
M22: Immobilisations incorporelles | Q22: Capital | R22: =L5+L6 -> 824758.53
M23: Frais d'Etablissements | N23: =1250+10000+10518+1250+5500+20000+82292.65+41282.51+80302.31 -> 252395.47 | O23: =(N23/48)*22 -> 115681.26 | P23: =N23-O23 -> 136714.21 | Q23: Reserves | R23: 0
M24: Amenagements et decorations | N24: =15000+11000 -> 26000 | O24: =(N24/18)*18 -> 26000 | P24: =N24-O24 -> 0 | Q24: Report a nouveau | R24: =-386036.46-13500-27500-37359.67-88819.54+33613.94-29972.5+87532.4+56880.81+36807.67+9938.26+10872.6+15048.45-17021.9-80209.31+88728.66+107539.05+32453.45-805.56+43896.68+11717.01-39847.93-7772.19 -> -193816.08
M25: Frais activation lapoula & impression | N25: =11650 -> 11650 | O25: =(N25/12)*10 -> 9708.3333 | P25: =N25-O25 -> 1941.6667 | Q25: Resultat | R25: =L7 -> -26388.286
M26: Autres | N26: 40964.3 | O26: =(N26/18)*18 -> 40964.3 | P26: =N26-O26 -> 0
M27: Immobilisations corporelles
M28: Materiel de bureau | N28: =20000+9000 -> 29000 | O28: =(N28/48)*22 -> 13291.667 | P28: =N28-O28 -> 15708.333
M29: Materiel et outillage | N29: =2500+750+1200+2000+15000+25000 -> 46450 | O29: =(N29/24)*22 -> 42579.167 | P29: =N29-O29 -> 3870.8333
M30: Materiel de transport | N30: 128000 | O30: =(N30/18)*18 -> 128000 | P30: =N30-O30 -> 0
M31: Autres | N31: =(5000+6000+9695) -> 20695 | O31: =(6000/12)*12+(9695/12)*8 -> 12463.333 | P31: =N31-O31 -> 8231.6667
M32: Immobilisations Financieres
M33: Loyer paye d'Avance | N33: 200000 | O33: =8333.33*23 -> 191666.59 | P33: =N33-O33 -> 8333.41
M34: Effet a recevoir | N34: =10000+6000 -> 16000 | P34: =N34 -> 16000
M36: Actif Circulant | Q36: Dettes
M37: Stocks | N37: =200290.05-11935.05 -> 188355 | P37: =N37 -> 188355 | Q37: Emprunt | R37: 0
M38: Disponibles | P38: =N41+N39+N40 -> 225399.05 | Q38: Dettes Fournisseurs | R38: 0
M39: Comptes Banques | N39: 1369 | Q39: Autres dettes | R39: 0
M40: Compte Lapoula | N40: 11935.05
M41: Caisse | N41: 212095
M42: Total Actif | N42: =SUM(N23:N39) -> 960878.77 | O42: =SUM(O23:O33) -> 580354.65 | P42: =SUM(P23:P38) -> 604554.17 | Q42: Total Passif | S42: =S21 -> 604554.17 | W42: =P42-S42 -> 0.0045833333
S46: =P42-S42 -> 0.0045833333
P49: =SUM(O23:O31) -> 388688.06 | X49: =20*11.51 -> 230.2
P50: =P49/8 -> 48586.007 | X50: =X49*12 -> 2762.4
X51: =1450*14 -> 20300
X52: =800+500 -> 1300
X53: =X50+X51+X52 -> 24362.4
X54: =84.88*0.75 -> 63.66
X55: =X54*12 -> 763.92
X56: =X53+X55 -> 25126.32
W59: Part des associes au 31 Oct 2025
W60: Prnom & Nom | X60: Montant invest | Y60: Montant Actuel | Z60: Pourcentage
W61: Hilaire BELLEVUE | X61: 817445 | Y61: =L8*Z61 -> 602370.35 | Z61: =75.45% -> 0.7545
W62: Luckner JEAN | X62: 151038 | Y62: =L8*Z62 -> 111292.81 | Z62: =13.94% -> 0.1394
W63: Nono ST-CYR | X63: 140000 | Y63: =L8*Z63 -> 84707.083 | Z63: =10.61% -> 0.1061
W64: Total | X64: =X61+X62+X63 -> 1108483 | Y64: =Y61+Y62+Y63 -> 798370.25 | Z64: =Z61+Z62+Z63 -> 1

Sheet NOV 2025 
B2: HLN Solutions | I2: HLN Solutions
B3: Etat des résultats | I3: Etat des capitaux propres
B4: Pour la periode terminant le 30 Nov 2025 | I4: Pour la période terminant le 30 Nov 2025
B5: VENTES BRUTES | E5: 24600 | I5: Capital initial | L5: 798370.25
B6: Cout des Marchandises Vendues(CMV) | C6: 19034.6 | I6: Apports | L6: 0
B7: Cout des Produits Vendus | E7: =C6 -> 19034.6 | I7: Perte nette | L7: =E18 -> 24249.104
B8: MARGE BENEFICIAIRE BRUTE | E8: =E5-C6 -> 5565.4 | I8: Capital au 30 Nov 2025 | L8: =SUM(L5:L7) -> 822619.35
B9: Couts d'exploitation
B10: Salaires | C10: 15000
B11: Loyer | C11: ='[1]Tableau d''amortissement loyer'!$D$4 -> 8333.3333
B12: Publicité | C12: =(20802.71/12)+(29040/12) -> 4153.5592
B13: Amortissements & Dépréciations | C13: =25692.72-2275.79-7111.11 -> 16305.82
B14: Autres depenses | C14: =11650/12 -> 970.83333
B15: Total des couts d'Exploitation | E15: =SUM(C10:D14) -> 44763.546
B16: Perte nette | E16: =E8-E15 -> -39198.146
B17: Revenus hors activites | C17: =1697.25+61750 -> 63447.25 | E17: =C17 -> 63447.25
B18: Résultat de la période | E18: =E16+E17 -> 24249.104 | M18: Bilan
M19: Au 30 Nov 2025
M20: ACTIF | N20: Brut | O20: Amort/ Deprec | P20: Net | Q20: PASSIF
M21: Actif Immobilisé | Q21: Capitaux Propres | S21: =+R22+R25+R24 -> 648887.03
M22: Immobilisations incorporelles | Q22: Capital | R22: =L5+L6 -> 798370.25
M23: Frais d'Etablissements | N23: =1250+10000+10518+1250+5500+20000+82292.65+41282.51+80302.31 -> 252395.47 | O23: =(N23/48)*23 -> 120939.5 | P23: =N23-O23 -> 131455.97 | Q23: Reserves | R23: 0
M24: Amenagements et decorations | N24: =15000+11000 -> 26000 | O24: =(N24/18)*18 -> 26000 | P24: =N24-O24 -> 0 | Q24: Report a nouveau | R24: =-386036.46-13500-27500-37359.67-88819.54+33613.94-29972.5+87532.4+56880.81+36807.67+9938.26+10872.6+15048.45-17021.9-80209.31+88728.66+107539.05+32453.45-805.56+43896.68+11717.01-39847.93-7772.19+20083.76 -> -173732.32
M25: Frais activation lapoula & impression | N25: =11650 -> 11650 | O25: =(N25/12)*11 -> 10679.167 | P25: =N25-O25 -> 970.83333 | Q25: Resultat | R25: =L7 -> 24249.104
M26: Autres | N26: 40964.3 | O26: =(N26/18)*18 -> 40964.3 | P26: =N26-O26 -> 0
M27: Immobilisations corporelles
M28: Materiel de bureau | N28: =20000+9000 -> 29000 | O28: =(N28/48)*23 -> 13895.833 | P28: =N28-O28 -> 15104.167
M29: Materiel et outillage | N29: =2500+750+1200+2000+15000+25000 -> 46450 | O29: =(N29/24)*23 -> 44514.583 | P29: =N29-O29 -> 1935.4167
M30: Materiel de transport | N30: 128000 | O30: =(N30/18)*18 -> 128000 | P30: =N30-O30 -> 0
M31: Autres | N31: =(5000+6000+9695) -> 20695 | O31: =(6000/12)*12+(9695/12)*9 -> 13271.25 | P31: =N31-O31 -> 7423.75
M32: Immobilisations Financieres
M33: Loyer paye d'Avance | N33: 200000 | O33: =8333.33*24 -> 199999.92 | P33: =N33 -> 200000
M34: Effet a recevoir | N34: =10000+6000 -> 16000 | P34: =N34 -> 16000
M36: Actif Circulant | Q36: Dettes
M37: Stocks | N37: =181255.45 -> 181255.45 | P37: =N37 -> 181255.45 | Q37: Emprunt | R37: 0
M38: Disponibles | P38: =N41+N39+N40 -> 94741.44 | Q38: Dettes Fournisseurs | R38: 0
M39: Comptes Banques | N39: 1369 | Q39: Autres dettes | R39: 0
M40: Compte Lapoula | N40: 9927.44
M41: Caisse | N41: 83445
M42: Total Actif | N42: =SUM(N23:N39) -> 953779.22 | O42: =SUM(O23:O33) -> 598264.55 | P42: =SUM(P23:P38) -> 648887.03 | Q42: Total Passif | S42: =S21 -> 648887.03 | W42: =P42-S42 -> -0.0035416668
S46: =P42-S42 -> -0.0035416668
P49: =SUM(O23:O31) -> 398264.63 | X49: =20*11.51 -> 230.2
P50: =P49/8 -> 49783.079 | X50: =X49*12 -> 2762.4
X51: =1450*14 -> 20300
X52: =800+500 -> 1300
X53: =X50+X51+X52 -> 24362.4
X54: =84.88*0.75 -> 63.66
X55: =X54*12 -> 763.92
X56: =X53+X55 -> 25126.32
W59: Part des associes au 30 Nov 2025
W60: Prnom & Nom | X60: Montant invest | Y60: Montant Actuel | Z60: Pourcentage
W61: Hilaire BELLEVUE | X61: 817445 | Y61: =L8*Z61 -> 620666.3 | Z61: =75.45% -> 0.7545
W62: Luckner JEAN | X62: 151038 | Y62: =L8*Z62 -> 114673.14 | Z62: =13.94% -> 0.1394
W63: Nono ST-CYR | X63: 140000 | Y63: =L8*Z63 -> 87279.913 | Z63: =10.61% -> 0.1061
W64: Total | X64: =X61+X62+X63 -> 1108483 | Y64: =Y61+Y62+Y63 -> 822619.35 | Z64: =Z61+Z62+Z63 -> 1
U69: Part des associes au 30 Nov 2025
U70: Prnom & Nom | V70: Montant invest | W70: Montant Actuel | X70: Pourcentage
U71: Hilaire BELLEVUE | V71: 817445 | W71: =620666 -> 620666 | X71: =W71/W75 -> 0.58409082
U72: Luckner JEAN | V72: 151038 | W72: =114673+40000 -> 154673 | X72: =W72/W75 -> 0.14555829
U73: Nono ST-CYR | V73: 140000 | W73: 87280 | X73: =W73/W75 -> 0.082136683
V74: 200000 | W74: 200000 | X74: =W74/W75 -> 0.18821421
U75: Total | V75: =V71+V72+V73 -> 1108483 | W75: =SUM(W71:W74) -> 1062619 | X75: =X71+X72+X73+X74 -> 1
Q78: =7500*12 -> 90000
